BeginnersbookMongodbJiaochengChuyiFix1/README.md
BeginnersbookMongodbJiaochengChuyiFix1/__init__.py
BeginnersbookMongodbJiaochengChuyiFix1/__main__.py
BeginnersbookMongodbJiaochengChuyiFix1/file.epub
BeginnersbookMongodbJiaochengChuyiFix1/index.html
BeginnersbookMongodbJiaochengChuyiFix1/css/__init__.py
BeginnersbookMongodbJiaochengChuyiFix1/css/annotations.css
BeginnersbookMongodbJiaochengChuyiFix1/css/main.css
BeginnersbookMongodbJiaochengChuyiFix1/css/normalize.css
BeginnersbookMongodbJiaochengChuyiFix1/css/popup.css
BeginnersbookMongodbJiaochengChuyiFix1/font/__init__.py
BeginnersbookMongodbJiaochengChuyiFix1/font/fontello.eot
BeginnersbookMongodbJiaochengChuyiFix1/font/fontello.svg
BeginnersbookMongodbJiaochengChuyiFix1/font/fontello.ttf
BeginnersbookMongodbJiaochengChuyiFix1/font/fontello.woff
BeginnersbookMongodbJiaochengChuyiFix1/img/__init__.py
BeginnersbookMongodbJiaochengChuyiFix1/img/annotator-glyph-sprite.png
BeginnersbookMongodbJiaochengChuyiFix1/img/annotator-icon-sprite.png
BeginnersbookMongodbJiaochengChuyiFix1/img/apple-touch-icon.png
BeginnersbookMongodbJiaochengChuyiFix1/img/cancelfullscreen.png
BeginnersbookMongodbJiaochengChuyiFix1/img/close.png
BeginnersbookMongodbJiaochengChuyiFix1/img/fullscreen.png
BeginnersbookMongodbJiaochengChuyiFix1/img/loader.gif
BeginnersbookMongodbJiaochengChuyiFix1/img/menu-icon.png
BeginnersbookMongodbJiaochengChuyiFix1/img/save.png
BeginnersbookMongodbJiaochengChuyiFix1/img/saved.png
BeginnersbookMongodbJiaochengChuyiFix1/img/settings-s.png
BeginnersbookMongodbJiaochengChuyiFix1/img/settings.png
BeginnersbookMongodbJiaochengChuyiFix1/img/star.png
BeginnersbookMongodbJiaochengChuyiFix1/js/__init__.py
BeginnersbookMongodbJiaochengChuyiFix1/js/epub.js
BeginnersbookMongodbJiaochengChuyiFix1/js/epub.min.js
BeginnersbookMongodbJiaochengChuyiFix1/js/epub.min.map
BeginnersbookMongodbJiaochengChuyiFix1/js/hooks.min.js
BeginnersbookMongodbJiaochengChuyiFix1/js/hooks.min.map
beginnersbook_mongodb_jiaocheng_chuyi_fix1-2025.3.24.0.dist-info/METADATA
beginnersbook_mongodb_jiaocheng_chuyi_fix1-2025.3.24.0.dist-info/WHEEL
beginnersbook_mongodb_jiaocheng_chuyi_fix1-2025.3.24.0.dist-info/entry_points.txt
beginnersbook_mongodb_jiaocheng_chuyi_fix1-2025.3.24.0.dist-info/top_level.txt
beginnersbook_mongodb_jiaocheng_chuyi_fix1-2025.3.24.0.dist-info/RECORD
